resourcies/__init__.py
resourcies/functions.py
resourcies/hello.py
resourcies-0.2.dist-info/METADATA
resourcies-0.2.dist-info/WHEEL
resourcies-0.2.dist-info/top_level.txt
resourcies-0.2.dist-info/RECORD
