Metadata-Version: 2.1
Name: resourcies
Version: 0.2
Summary: misc package
Home-page: https://github.com/robertCodedIt/resources.git/
Author: robertCodedIt
Author-email: robertlove99999@gmail.com
License: MIT
Platform: UNKNOWN
